Metadata-Version: 2.1
Name: q-random-number-generator
Version: 0.1.0
Summary: Using qiskit to realize random number generator.
Home-page: https://github.com/allen91wu/q_random_number_generator
Author: Allen Wu
Author-email: allen91.wu@gmail.com
Classifier: Programming Language :: Python :: 3
Classifier: License :: OSI Approved :: MIT License
Requires-Python: >=3.8
License-File: LICENSE
